datakaryawan/__init__.py
datakaryawan/admin.py
datakaryawan/apps.py
datakaryawan/models.py
datakaryawan/tests.py
datakaryawan/views.py
datakaryawan/migrations/__init__.py
el_user-0.1.dist-info/METADATA
el_user-0.1.dist-info/RECORD
el_user-0.1.dist-info/WHEEL
el_user-0.1.dist-info/top_level.txt
